mycalc/calculator.py
0411_test-1.0.1.dist-info/METADATA
0411_test-1.0.1.dist-info/WHEEL
0411_test-1.0.1.dist-info/top_level.txt
0411_test-1.0.1.dist-info/RECORD
