Metadata-Version: 2.1
Name: 0411-test
Version: 1.0.1
Summary: nice calc
Home-page: http://github.com/seonghun0915
Download-URL: 
License: UNKNOWN
Platform: UNKNOWN
Classifier: Programming Language :: Python :: 3
